MANIFEST.in
README.rst
setup.py
django_shotgun/__init__.py
django_shotgun/models.py
django_shotgun/settings.py
django_shotgun/tests.py
django_shotgun.egg-info/PKG-INFO
django_shotgun.egg-info/SOURCES.txt
django_shotgun.egg-info/dependency_links.txt
django_shotgun.egg-info/not-zip-safe
django_shotgun.egg-info/requires.txt
django_shotgun.egg-info/top_level.txt
django_shotgun/management/__init__.py
django_shotgun/management/commands/__init__.py
django_shotgun/management/commands/load_shotgun.py