Metadata-Version: 1.0
Name: django-shotgun
Version: 0.2
Summary: A Django application for testing entire sites.
Home-page: http://github.com/stephenmcd/django-shotgun
Author: Stephen McDonald
Author-email: stephen.mc@gmail.com
License: UNKNOWN
Platform: UNKNOWN
Classifier: Development Status :: 5 - Production/Stable
Classifier: Environment :: Web Environment
Classifier: Intended Audience :: Developers
Classifier: Operating System :: OS Independent
Classifier: Programming Language :: Python
Classifier: Framework :: Django
Classifier: Topic :: Internet :: WWW/HTTP :: Dynamic Content
Classifier: Topic :: Internet :: WWW/HTTP :: Site Management
